plotly_gruvbox_colorscheme/__init__.py
plotly_gruvbox_colorscheme-0.2.0.dist-info/LICENSE
plotly_gruvbox_colorscheme-0.2.0.dist-info/METADATA
plotly_gruvbox_colorscheme-0.2.0.dist-info/WHEEL
plotly_gruvbox_colorscheme-0.2.0.dist-info/top_level.txt
plotly_gruvbox_colorscheme-0.2.0.dist-info/zip-safe
plotly_gruvbox_colorscheme-0.2.0.dist-info/RECORD
